{
    "top500": false,
    "parts_sold": {
        "Shock Absorber": 3
    },
    "specific_parts_sold": {
        "Shock absorber": 3
    },
    "buyers": {
        "Dongfeng Liuzhou Motor:Shock Absorber": 3
    },
    "Country": "China",
    "Address": "405, 4th Floor, Building 4, No.46, Jinhaian Avenue West, Sanzao Town, Jinwan District,  Zhuhai, Guangdong, China",
    "TEL": "+86-15014901269",
    "Year established": "Aug,1993",
    "URL": "http://www.cncclutch.com",
    "Quality certification": "ISO9001QS9000VDA6.1IATF16949 (Formerly ISO/TS16949)",
    "Environmental certification": "ISO14001",
    "Remarks": "-Shareholder(s): Zhuhai HuaHuo Transmission Technology Co., Ltd.CHINA AND CANTON (HOLDINGS) COMPANY LIMITED"
}