{
    "top500": false,
    "parts_sold": {
        "Shock Absorber": 9
    },
    "specific_parts_sold": {
        "Shock absorber": 9
    },
    "buyers": {
        "BYD:Shock Absorber": 9
    },
    "Country": "China",
    "Address": "BYD Auto Base, Shatang Community, Maluan Street, Pingshan District, Shenzhen City, Guangdong Province, China",
    "TEL": "+86-755-89888888",
    "Year established": "Dec. 2019",
    "URL": "https://www.bydglobal.com/",
    "Quality certification": "IATF16949 (Formerly ISO/TS16949)",
    "Environmental certification": "ISO14001",
    "Remarks": "-Shareholder(s): BYD Co., Ltd.-Wire harness factories: Shenzhen, Xi'an, Changsha, Shangluo, Guilin, Guang'an, Anyang, Fuzhou, Fuyang, Huizhou-Wire harness R&D Center: Shenzhen, Xi'an, Hefei"
}