{
    "top500": false,
    "parts_sold": {
        "Wiring Harness": 27
    },
    "specific_parts_sold": {
        "Interior wiring harness": 1,
        "Body wiring harness": 1,
        "Wiring harness for anti-theft alarm": 2,
        "ABS wiring harness": 2,
        "High-voltage wiring harness": 2,
        "Shock absorber wiring harness": 4,
        "Harness for brake pad sensor": 4,
        "Rear view mirror wiring harness": 1,
        "Door handle wiring harness": 2,
        "Wiring harness for adaptive cruise control": 1,
        "Door harness": 1,
        "Wiring harness": 6
    },
    "buyers": {
        "Mercedes-Benz": 6,
        "BMW": 9,
        "Daimler": 9,
        "Audi": 2,
        "Porsche": 1
    },
    "Country": "Austria",
    "Address": "Oberer Paspelsweg 6-8, A-6830 Rankweil, Austria",
    "TEL": "+43-552-230-70",
    "URL": "https://www.hirschmann-automotive.com",
    "Quality certification": "ISO9001QS9000"
}