{
    "top500": true,
    "parts_sold": [
        "Rear Lamp"
    ],
    "specific_parts_sold": [
        "Rear lamp"
    ],
    "buyers": [
        "FAW-Volkswagen"
    ],
    "Year Established": "Oct. 1992",
    "Number of Employees": "6,719 employees (as of Dec. 31, 2023)",
    "Sales Turnover": "CNY 168,594.05 million (FY ended Dec. 31, 2023)",
    "Representative": "Chairman: Hong CHEN",
    "URL": "http://www.hasco-group.com/",
    "Address": "No. 489, Weihai Road, Jing'an District, Shanghai, China"
}