{
    "top500": false,
    "parts_sold": {
        "Wiring Harness": 2
    },
    "specific_parts_sold": {
        "Rear view mirror wiring harness": 1,
        "Interior mirror wiring harness": 1
    },
    "buyers": {
        "Tesla China": 2
    },
    "Country": "China",
    "Address": "Fangmao Village, Hengshanqiao Town, Economic Development Zone, Changzhou City, Jiangsu Province, China",
    "TEL": "+86-519-68850588",
    "Year established": "Aug. 1998",
    "URL": "https://www.riyingcorp.com/",
    "Quality certification": "IATF16949 (Formerly ISO/TS16949)",
    "Environmental certification": "ISO14001"
}