{
    "top500": false,
    "parts_sold": {
        "Rear Lamp": 15
    },
    "specific_parts_sold": {
        "Rear combination lamp": 14,
        "Rear lamp": 1
    },
    "buyers": {
        "Changan": 6,
        "Deepal": 2,
        "SAIC GM Wuling": 2,
        "SERES": 2,
        "Changhe": 1,
        "Dongfeng Liuzhou Motor": 1,
        "Lifan": 1
    },
    "Country": "China",
    "Address": "No.26, Zhenhua Road, Nanning, Guangxi, China",
    "TEL": "+86-771-5665299",
    "Year established": "Apr. 1993",
    "URL": "http://www.lwcd.com.cn",
    "Quality certification": "IATF16949 (Formerly ISO/TS16949)",
    "Environmental certification": "ISO14001",
    "Remarks": "-Shareholder(s): Foshan Electrical and Lighting Co., Ltd."
}