{
    "top500": true,
    "parts_sold": {
        "Axle": 10
    },
    "specific_parts_sold": {
        "Rear pipe structure axle beam": 1,
        "Rear axle beam": 8,
        "Twist beam rear axle": 1
    },
    "buyers": {
        "Renault Samsung:Axle": 1,
        "Honda:Axle": 7,
        "Nissan:Axle": 2
    },
    "Year Established": "Apr. 1, 1948",
    "Number of Employees": ",726 employees (As of Mar. 31, 2023)",
    "Sales Turnover": "JPY 181,468 million (FY ended Mar. 31, 2024)",
    "Representative": "Tsutomu Hiranaka (President and COO)",
    "Capital": "JPY 6,200 million (As of Mar. 31, 2023)",
    "URL": "http://www.yorozu-corp.co.jp/en/",
    "Address": "3-7-60 Tarumachi, Kohoku-ku, Yokohama-shi, Kanagawa 222-8560, Japan",
    "Country": "Japan"
}