{
    "top500": false,
    "parts_sold": {
        "Shock Absorber": 6
    },
    "specific_parts_sold": {
        "Rear shock absorber": 3,
        "Continuous damping control(1.5T)": 1,
        "Shock absorber": 2
    },
    "buyers": {
        "GM:Shock Absorber": 3,
        "Li Auto:Shock Absorber": 1,
        "Xpeng:Shock Absorber": 2
    },
    "Country": "China",
    "Address": "No. 4440, Yuanjiang Road, Minhang District, Shanghai, 201111 China",
    "TEL": "+86-21-24169459",
    "Year established": "Apr. 1998",
    "URL": "https://www.zf.com/",
    "Quality certification": "ISO9001IATF16949 (Formerly ISO/TS16949)",
    "Environmental certification": "ISO14001",
    "Remarks": "-Shareholders:  ZF China Investment Co., Ltd. 100%"
}